aider_mcp_server/__init__.py
aider_mcp_server/__main__.py
aider_mcp_server/server.py
aider_mcp_server/atoms/__init__.py
aider_mcp_server/atoms/data_types.py
aider_mcp_server/atoms/logging.py
aider_mcp_server/atoms/utils.py
aider_mcp_server/atoms/tools/__init__.py
aider_mcp_server/atoms/tools/aider_ai_code.py
aider_mcp_server/atoms/tools/aider_list_models.py
aider_mcp_server/tests/__init__.py
aider_mcp_server/tests/atoms/__init__.py
aider_mcp_server/tests/atoms/test_logging.py
aider_mcp_server/tests/atoms/tools/__init__.py
aider_mcp_server/tests/atoms/tools/test_aider_ai_code.py
aider_mcp_server/tests/atoms/tools/test_aider_list_models.py
mseep_aider_mcp_server-0.1.4.dist-info/METADATA
mseep_aider_mcp_server-0.1.4.dist-info/WHEEL
mseep_aider_mcp_server-0.1.4.dist-info/entry_points.txt
mseep_aider_mcp_server-0.1.4.dist-info/top_level.txt
mseep_aider_mcp_server-0.1.4.dist-info/RECORD
